README.md
setup.cfg
setup.py
simplog/__init__.py
simplog/logger.py
simplog.egg-info/PKG-INFO
simplog.egg-info/SOURCES.txt
simplog.egg-info/dependency_links.txt
simplog.egg-info/top_level.txt