Metadata-Version: 2.1
Name: simplog
Version: 0.1.0
Summary: A simple, functional, opinionated logger for python
Home-page: https://github.com/JoelAtDeluxe/simplog
Author: Joel Smith
Author-email: joel.pypi@gmail.com
License: MIT
Download-URL: https://github.com/JoelAtDeluxe/simplog/archive/v0.1.0.tar.gz
Keywords: logging,functional,splunk
Platform: UNKNOWN
Classifier: Programming Language :: Python :: 3
Classifier: Development Status :: 4 - Beta
Classifier: Operating System :: OS Independent
Classifier: Intended Audience :: Developers
Classifier: License :: OSI Approved :: MIT License
